dj_component_view.py
dj_component_view-9.0.dist-info/LICENSE
dj_component_view-9.0.dist-info/WHEEL
dj_component_view-9.0.dist-info/METADATA
dj_component_view-9.0.dist-info/RECORD
