Metadata-Version: 2.1
Name: dj_component_view
Version: 9.0
Summary: Django component view for jinjax
Author-email: Stephan Fitzpatrick <knowsuchagency@gmail.com>
Classifier: License :: OSI Approved :: MIT License
Requires-Dist: django
Requires-Dist: jinjax
Project-URL: Source, https://github.com/knowsuchagency/dj_component_view
